aio_code_editor/__init__.py
aio_code_editor/app.py
aio_code_editor/css.py
aio_code_editor/shark.png
aio_code_editor/ui.py
aio_code_editor/until.py
aio_code_editor-0.7.2.dist-info/METADATA
aio_code_editor-0.7.2.dist-info/WHEEL
aio_code_editor-0.7.2.dist-info/RECORD
