Metadata-Version: 2.1
Name: aio-code-editor
Version: 0.7.2
Summary: 
Author: NguyenDinhTiem
Author-email: nguyendinhtiem1999@gmail.com
Requires-Python: >=3.8,<4.0
Classifier: Programming Language :: Python :: 3
Classifier: Programming Language :: Python :: 3.8
Classifier: Programming Language :: Python :: 3.9
Classifier: Programming Language :: Python :: 3.10
Classifier: Programming Language :: Python :: 3.11
Classifier: Programming Language :: Python :: 3.12
Requires-Dist: requests (>=2.31.0,<3.0.0)
Requires-Dist: streamlit (>=1.32.2,<2.0.0)
Requires-Dist: streamlit-code-editor (>=0.1.12,<0.2.0)
